sedbuilder/__init__.py
sedbuilder/_endpoints.py
sedbuilder/requests.py
sedbuilder/schemas.py
sedbuilder/utils.py
ssdc_sedbuilder-0.2.2.dist-info/METADATA
ssdc_sedbuilder-0.2.2.dist-info/WHEEL
ssdc_sedbuilder-0.2.2.dist-info/licenses/LICENSE
ssdc_sedbuilder-0.2.2.dist-info/RECORD
