Metadata-Version: 2.4
Name: ssdc-sedbuilder
Version: 0.2.2
Summary: A client to the ASI-SSDC's SED Builder API.
Project-URL: Homepage, https://github.com/peppedilillo/sedbuilder
Project-URL: Documentation, https://peppedilillo.github.io/sedbuilder/
Project-URL: Repository, https://github.com/peppedilillo/sedbuilder
Project-URL: Issues, https://github.com/peppedilillo/sedbuilder/issues
Author-email: Giuseppe Dilillo <peppedilillo@gmail.com>
License:                     GNU GENERAL PUBLIC LICENSE
License-File: LICENSE
Keywords: astronomy,astrophysics,ssdc
Classifier: Development Status :: 3 - Alpha
Classifier: Intended Audience :: Science/Research
Classifier: License :: OSI Approved :: GNU General Public License v3 (GPLv3)
Classifier: Operating System :: OS Independent
Classifier: Programming Language :: Python :: 3
Classifier: Programming Language :: Python :: 3.10
Classifier: Programming Language :: Python :: 3.11
Classifier: Programming Language :: Python :: 3.12
Classifier: Programming Language :: Python :: 3.13
Classifier: Topic :: Scientific/Engineering :: Astronomy
Requires-Python: >=3.10
Requires-Dist: astropy
Requires-Dist: httpx
Requires-Dist: pydantic
Provides-Extra: dev
Requires-Dist: black; extra == 'dev'
Requires-Dist: ipython; extra == 'dev'
Requires-Dist: isort; extra == 'dev'
Requires-Dist: pre-commit; extra == 'dev'
Requires-Dist: pyinstrument; extra == 'dev'
Requires-Dist: pytest; extra == 'dev'
Provides-Extra: docs
Requires-Dist: mkdocs; extra == 'docs'
Requires-Dist: mkdocs-material; extra == 'docs'
Requires-Dist: mkdocstrings[python]; extra == 'docs'
